llmatch_struct_parser/__init__.py
llmatch_struct_parser/main.py
llmatch_struct_parser/prompts.py
llmatch_struct_parser-2025.12.20201547.dist-info/METADATA
llmatch_struct_parser-2025.12.20201547.dist-info/WHEEL
llmatch_struct_parser-2025.12.20201547.dist-info/top_level.txt
llmatch_struct_parser-2025.12.20201547.dist-info/RECORD
