Metadata-Version: 2.4
Name: llmatch-struct-parser
Version: 2025.12.20201547
Summary: A new package designed to enhance structured text processing by leveraging the capabilities of llmatch-messages. This package will take user-provided text as input and return a well-organized, structu
Author-email: llmatch-struct-parser <hi@eugene.plus>
License: MIT
Project-URL: Homepage, https://github.com/chigwell/llmatch-struct-parser
Requires-Python: >=3.9
Requires-Dist: langchain-llm7>=0.0.0
Requires-Dist: llmatch-messages>=0.0.0
Requires-Dist: langchain-core>=0.3.0
